{
"__comment":"Made by Know2Good, part of the 'Default 3D' resource pack || Official download page: http://www.planetminecraft.com/texture_pack/default-3d-2985741/ || © Know2Good. All rights reserved. ",
    "variants": {
        "facing=north": [ { "model": "block/wood/ladder/0", "weight": 1 },
						  { "model": "block/wood/ladder/1", "weight": 1 },
						  { "model": "block/wood/ladder/2", "weight": 1 },
						  { "model": "block/wood/ladder/3", "weight": 1 },
						  { "model": "block/wood/ladder/4", "weight": 1 },
						  { "model": "block/wood/ladder/5", "weight": 1 },
						  { "model": "block/wood/ladder/6", "weight": 1 },
						  { "model": "block/wood/ladder/7", "weight": 1 },
						  { "model": "block/wood/ladder/8", "weight": 1 },
						  { "model": "block/wood/ladder/9", "weight": 1 },
						  { "model": "block/wood/ladder/10", "weight": 1 },
						  { "model": "block/wood/ladder/11", "weight": 1 },
						  { "model": "block/wood/ladder/12", "weight": 1 },
						  { "model": "block/wood/ladder/13", "weight": 1 }],
        "facing=east": 	[ { "model": "block/wood/ladder/0", "y": 90, "weight": 1 },
						  { "model": "block/wood/ladder/1", "y": 90, "weight": 1 },
						  { "model": "block/wood/ladder/2", "y": 90, "weight": 1 },
						  { "model": "block/wood/ladder/3", "y": 90, "weight": 1 },
						  { "model": "block/wood/ladder/4", "y": 90, "weight": 1 },
						  { "model": "block/wood/ladder/5", "y": 90, "weight": 1 },
						  { "model": "block/wood/ladder/6", "y": 90, "weight": 1 },
						  { "model": "block/wood/ladder/7", "y": 90, "weight": 1 },
						  { "model": "block/wood/ladder/8", "y": 90, "weight": 1 },
						  { "model": "block/wood/ladder/9", "y": 90, "weight": 1 },
						  { "model": "block/wood/ladder/10", "y": 90, "weight": 1 },
						  { "model": "block/wood/ladder/11", "y": 90, "weight": 1 },
						  { "model": "block/wood/ladder/12", "y": 90, "weight": 1 },
						  { "model": "block/wood/ladder/13", "y": 90, "weight": 1 }],
        "facing=south": [ { "model": "block/wood/ladder/0", "y": 180, "weight": 1 },
						  { "model": "block/wood/ladder/1", "y": 180, "weight": 1 },
						  { "model": "block/wood/ladder/2", "y": 180, "weight": 1 },
						  { "model": "block/wood/ladder/3", "y": 180, "weight": 1 },
						  { "model": "block/wood/ladder/4", "y": 180, "weight": 1 },
						  { "model": "block/wood/ladder/5", "y": 180, "weight": 1 },
						  { "model": "block/wood/ladder/6", "y": 180, "weight": 1 },
						  { "model": "block/wood/ladder/7", "y": 180, "weight": 1 },
						  { "model": "block/wood/ladder/8", "y": 180, "weight": 1 },
						  { "model": "block/wood/ladder/9", "y": 180, "weight": 1 },
						  { "model": "block/wood/ladder/10", "y": 180, "weight": 1 },
						  { "model": "block/wood/ladder/11", "y": 180, "weight": 1 },
						  { "model": "block/wood/ladder/12", "y": 180, "weight": 1 },
						  { "model": "block/wood/ladder/13", "y": 180, "weight": 1 }],
        "facing=west": 	[ { "model": "block/wood/ladder/0", "y": 270, "weight": 1 },
						  { "model": "block/wood/ladder/1", "y": 270, "weight": 1 },
						  { "model": "block/wood/ladder/2", "y": 270, "weight": 1 },
						  { "model": "block/wood/ladder/3", "y": 270, "weight": 1 },
						  { "model": "block/wood/ladder/4", "y": 270, "weight": 1 },
						  { "model": "block/wood/ladder/5", "y": 270, "weight": 1 },
						  { "model": "block/wood/ladder/6", "y": 270, "weight": 1 },
						  { "model": "block/wood/ladder/7", "y": 270, "weight": 1 },
						  { "model": "block/wood/ladder/8", "y": 270, "weight": 1 },
						  { "model": "block/wood/ladder/9", "y": 270, "weight": 1 },
						  { "model": "block/wood/ladder/10", "y": 270, "weight": 1 },
						  { "model": "block/wood/ladder/11", "y": 270, "weight": 1 },
						  { "model": "block/wood/ladder/12", "y": 270, "weight": 1 },
						  { "model": "block/wood/ladder/13", "y": 270, "weight": 1 }]
    }
}
